Project 1 - Half Adder/src/verilog/half_adder.v
module half_adder(
    input wire a,
    input wire b,
    output wire sum,
    output wire cout
);

assign sum = a ^ b;
assign cout = a * b;

endmodule

Project 2 - Full Adder/src/verilog/full_adder.v
`include "../../../Project 1 - Half Adder/src/verilog/half_adder.v"
module full_adder(
    input wire a,
    input wire b,
    input wire cin,
    output wire sum,
    output wire cout
);

wire ha0_sum;
wire ha0_cout;

half_adder ha0(
    .a(a),
    .b(b),
    .sum(ha0_sum),
    .cout(ha0_cout)
);

wire ha1_cout;

half_adder hf1(
    .a(cin),
    .b(ha0_sum),
    .sum(sum),
    .cout(ha1_cout)
);

assign cout = ha1_cout | ha0_cout;

endmodule

Project 2 - Full Adder/test/verilog/full_adder_tb.v
`timescale 1ps/1ps
//`include "../../../Project 1 - Half Adder/src/verilog/half_adder.v"
`include "../../src/verilog/full_adder.v"
module full_adder_tb;

reg a_tb;
reg b_tb;
reg cin_tb;
wire sum_tb;
wire cout_tb;

full_adder fa0(
    .a(a_tb),
    .b(b_tb),
    .cin(cin_tb),
    .sum(sum_tb),
    .cout(cout_tb)
);

task verify;
    input a_task;
    input b_task;
    input cin_task;
    input sum_task;
    input cout_task;

    begin
        a_tb = a_task;
        b_tb = b_task;
        cin_tb = cin_task;
        #1;
        if(sum_task == sum_tb && cout_task == cout_tb) begin
            $display("CORRECTO: Dato de entrada a: %b, Dato de entrada b: %b, Dato de entrada cin: %b, Dato de salida s esperado: %b, Dato de salida s obtenido: %b, Dato de salida c esperado: %b, Dato de salida c obtenido: %b", a_tb, b_tb, cin_task, sum_task, sum_tb, cout_task, cout_tb);
        end else begin
            $display("INCORRECTO: Dato de entrada a: %b, Dato de entrada b: %b, Dato de entrada cin: %b, Dato de salida s esperado: %b, Dato de salida s obtenido: %b, Dato de salida c esperado: %b, Dato de salida c obtenido: %b", a_tb, b_tb, cin_task, sum_task, sum_tb, cout_task, cout_tb);

        end
    end

endtask

initial begin
  $dumpfile("full_adder_tb.vcd");
  $dumpvars(0, full_adder_tb);
end

initial begin

verify(
    1'b0,
    1'b0,
    1'b0,
    1'b0,
    1'b0
);

verify(
    1'b0,
    1'b0,
    1'b1,
    1'b1,
    1'b0
);

verify(
    1'b0,
    1'b1,
    1'b0,
    1'b1,
    1'b0
);

verify(
    1'b0,
    1'b1,
    1'b1,
    1'b0,
    1'b1
);

verify(
    1'b1,
    1'b0,
    1'b0,
    1'b1,
    1'b0
);

verify(
    1'b1,
    1'b0,
    1'b1,
    1'b0,
    1'b1
);

verify(
    1'b1,
    1'b1,
    1'b0,
    1'b0,
    1'b1
);

verify(
    1'b1,
    1'b1,
    1'b1,
    1'b1,
    1'b1
);

end

endmodule

Project 2 - Full Adder/test/verilog/full_adder_tb.vcd
$date
	Sat Jan 13 10:46:46 2024
$end
$version
	Icarus Verilog
$end
$timescale
	1ps
$end
$scope module full_adder_tb $end
$var wire 1 ! sum_tb $end
$var wire 1 " cout_tb $end
$var reg 1 # a_tb $end
$var reg 1 $ b_tb $end
$var reg 1 % cin_tb $end
$scope module fa0 $end
$var wire 1 # a $end
$var wire 1 $ b $end
$var wire 1 % cin $end
$var wire 1 " cout $end
$var wire 1 ! sum $end
$var wire 1 & ha1_cout $end
$var wire 1 ' ha0_sum $end
$var wire 1 ( ha0_cout $end
$scope module ha0 $end
$var wire 1 # a $end
$var wire 1 $ b $end
$var wire 1 ' sum $end
$var wire 1 ( cout $end
$upscope $end
$scope module hf1 $end
$var wire 1 % a $end
$var wire 1 ' b $end
$var wire 1 ! sum $end
$var wire 1 & cout $end
$upscope $end
$upscope $end
$scope task verify $end
$var reg 1 ) a_task $end
$var reg 1 * b_task $end
$var reg 1 + cin_task $end
$var reg 1 , cout_task $end
$var reg 1 - sum_task $end
$upscope $end
$upscope $end
$enddefinitions $end
$comment Show the parameter values. $end
$dumpall
$end
#0
$dumpvars
0-
0,
0+
0*
0)
0(
0'
0&
0%
0$
0#
0"
0!
$end
#1
1!
1%
1-
1+
#2
1'
0%
1$
0+
1*
#3
0!
1"
1&
1%
1,
0-
1+
#4
1!
0"
0&
0%
0$
0(
1#
0,
1-
0+
0*
1)
#5
0!
1"
1&
1%
1,
0-
1+
#6
0'
0&
0%
1(
1$
0+
1*
#7
1!
1%
1-
1+
